README.txt
setup.py
datautil/__init__.py
datautil/cache.py
datautil/clitools.py
datautil/date.py
datautil/deliveranceproxy.py
datautil/id.py
datautil/misc.py
datautil/scrape.py
datautil.egg-info/PKG-INFO
datautil.egg-info/SOURCES.txt
datautil.egg-info/dependency_links.txt
datautil.egg-info/not-zip-safe
datautil.egg-info/requires.txt
datautil.egg-info/top_level.txt
datautil/parse/__init__.py
datautil/parse/name.py
datautil/tabular/__init__.py
datautil/tabular/base.py
datautil/tabular/gdocs.py
datautil/tabular/html.py
datautil/tabular/misc.py
datautil/tabular/tabular_json.py
datautil/tabular/txt.py
datautil/tabular/xls.py
datautil/tests/__init__.py
datautil/tests/test_cache.py
datautil/tests/test_date.py
datautil/tests/test_id.py
datautil/tests/test_misc.py
datautil/tests/test_xls.py
datautil/tests/tabular/__init__.py
datautil/tests/tabular/test_base.py
datautil/tests/tabular/test_gdocs.py
datautil/tests/tabular/test_json.py
datautil/tests/tabular/test_misc.py
datautil/tests/tabular/test_txt.py
swiss/__init__.py
toadd/__init__.py
toadd/plot.py
toadd/plot_test.py