Metadata-Version: 1.0
Name: datautil
Version: 0.4
Summary: Utilities Data Work
Home-page: http://okfn.org/projects/datautil/
Author: Open Knowledge Foundation
Author-email: info@okfn.org
License: MIT
Download-URL: http://bitbucket.org/okfn/datautil/
Platform: UNKNOWN
Classifier: Development Status :: 5 - Production/Stable
Classifier: Environment :: Console
Classifier: Intended Audience :: Developers
Classifier: Operating System :: OS Independent
Classifier: Programming Language :: Python
Classifier: Topic :: Software Development :: Libraries :: Python Modules
